kisti_dongmin_text_writer/__init__.py
kisti_dongmin_text_writer/server.py
kisti_dongmin_text_writer-0.4.0.dist-info/METADATA
kisti_dongmin_text_writer-0.4.0.dist-info/WHEEL
kisti_dongmin_text_writer-0.4.0.dist-info/entry_points.txt
kisti_dongmin_text_writer-0.4.0.dist-info/RECORD
