Metadata-Version: 2.4
Name: kisti-dongmin-text-writer
Version: 0.4.0
Summary: Add your description here
Requires-Python: >=3.11
Requires-Dist: build>=1.3.0
Requires-Dist: mcp[cli]>=1.12.3
Requires-Dist: twine>=6.1.0
